{
  "variant_key": "vpvr_reversion_1m_volume_profile_break_20260709",
  "iteration": 69,
  "version": "V5",
  "symbol": "BTCUSDT",
  "n_bars": 1140075,
  "span_start": "2024-04-23 00:00:00+00:00",
  "span_end": "2026-06-23 17:14:00+00:00",
  "starting_capital_usd": 100000.0,
  "ending_capital_usd": 97334.23910562406,
  "n_trades": 6751,
  "n_wins": 1252,
  "n_losses": 5499,
  "win_rate": 0.1855,
  "sharpe": -22.6541,
  "ann_return_pct": -1.2379,
  "max_drawdown_pct": -2.6685,
  "profit_factor": 0.116,
  "criteria": {
    "sharpe": {
      "min": 1.0,
      "actual": -22.6541,
      "pass": false
    },
    "ann_return_pct": {
      "min": 15.0,
      "actual": -1.2379,
      "pass": false
    },
    "max_drawdown_pct": {
      "min": -25.0,
      "actual": -2.6685,
      "pass": true
    },
    "profit_factor": {
      "min": 1.5,
      "actual": 0.116,
      "pass": false
    },
    "n_trades": {
      "min": 200,
      "actual": 6751,
      "pass": true
    }
  },
  "status": "NOT-PROFITABLE",
  "data_source": "data/fapi_BTCUSDT__1m.parquet",
  "note": "B3 run on real BTCUSDT 1m Binance USD-M data.",
  "generated_at": "2026-07-16T16:21:19.211268+00:00"
}