{
  "strategy": "vpvr_funding_term_curve_1h_20260714",
  "iteration": 97,
  "variant": "V1_funding_term_curve",
  "date": "2026-07-14",
  "timeframe": "1h",
  "instruments": [
    "BTCUSDT",
    "ETHUSDT"
  ],
  "axis": "funding_term_curve_steepness_z_spread_with_vpvr_poc_directional_filter",
  "tag": "NOT-PROFITABLE",
  "per_symbol": [
    {
      "n_trades": 1314,
      "win_rate": 0.3858447488584475,
      "profit_factor": 0.7803533356151954,
      "avg_hold_bars": 7.951293759512938,
      "total_return_pct": -0.8094717054410983,
      "sharpe": -1.1978937570674988,
      "sortino": -1.8974864166349654,
      "max_drawdown_pct": -0.8464427963164732,
      "trades_per_year": 290.3281458874568,
      "tag": "NOT-PROFITABLE",
      "exit_reasons": {
        "hard_stop": 828,
        "time_stop": 258,
        "atr_trail": 228
      },
      "symbol": "BTCUSDT",
      "span_start": "2022-01-01 00:00:00",
      "span_end": "2026-07-10 23:00:00",
      "n_bars": 39647
    },
    {
      "n_trades": 1262,
      "win_rate": 0.3977812995245642,
      "profit_factor": 0.8745884334088326,
      "avg_hold_bars": 9.0459587955626,
      "total_return_pct": -0.7534980387555095,
      "sharpe": -0.6389680808073748,
      "sortino": -0.9663038163016026,
      "max_drawdown_pct": -0.7903607651996152,
      "trades_per_year": 278.8317191283293,
      "tag": "NOT-PROFITABLE",
      "exit_reasons": {
        "atr_trail": 236,
        "hard_stop": 735,
        "time_stop": 291
      },
      "symbol": "ETHUSDT",
      "span_start": "2022-01-01 00:00:00",
      "span_end": "2026-07-10 23:00:00",
      "n_bars": 39648
    }
  ]
}